{
  "name": "Module",
  "base": "PersistedModel",
  "strict": false,
  "idInjection": false,
  "options": {
    "validateUpsert": true
  },
  "properties": {
    "id": {
      "type": "number",
      "id": true,
      "required": true,
      "index": true
    },
    "plugin_id": {
      "type": "number",
      "id": true,
      "required": true
    },
    "plugin_output_id": {
      "type": "number",
      "id": true,
      "comments": "This id is the output point before this module"
    },
    "config": {
      "type": "string",
      "required": true,
      "comments": "Config into JSON format"
    }
  },
  "validations": [],
  "relations": {},
  "acls": [],
  "methods": []
}
